{"id":"fasthar","github":"https://github.com/yowainwright/fasthar","current":{"stars":0,"forks":0,"commits":[{"year":2025,"count":7}],"downloads":{"monthly":0,"yearly":0,"allTime":0},"activity":{"total":7,"years":[{"year":2025,"count":7}],"months":[{"month":"2025-09","commits":1},{"month":"2025-10","commits":1},{"month":"2025-11","commits":5}]},"openIssues":0,"contributors":1,"bundleSize":0},"history":[{"date":"2025-12-25","stars":0,"forks":0,"downloads":{"monthly":0,"yearly":0,"allTime":0},"commits":[]},{"date":"2025-12-26","stars":0,"forks":0,"downloads":{"monthly":0,"yearly":0,"allTime":0},"commits":[]},{"date":"2025-12-27","stars":0,"forks":0,"downloads":{"monthly":0,"yearly":0,"allTime":0},"commits":[]},{"date":"2025-12-28","stars":0,"forks":0,"downloads":{"monthly":0,"yearly":0,"allTime":0},"commits":[]},{"date":"2025-12-29","stars":0,"forks":0,"downloads":{"monthly":0,"yearly":0,"allTime":0},"commits":[]},{"date":"2025-12-30","stars":0,"forks":0,"downloads":{"monthly":0,"yearly":0,"allTime":0},"commits":[]},{"date":"2025-12-31","stars":0,"forks":0,"downloads":{"monthly":0,"yearly":0,"allTime":0},"commits":[]},{"date":"2026-01-01","stars":0,"forks":0,"downloads":{"monthly":0,"yearly":0,"allTime":0},"commits":[]},{"date":"2026-01-02","stars":0,"forks":0,"downloads":{"monthly":0,"yearly":0,"allTime":0},"commits":[]},{"date":"2026-01-03","stars":0,"forks":0,"downloads":{"monthly":0,"yearly":0,"allTime":0},"commits":[]},{"date":"2026-01-04","stars":0,"forks":0,"downloads":{"monthly":0,"yearly":0,"allTime":0},"commits":[]},{"date":"2026-01-05","stars":0,"forks":0,"downloads":{"monthly":0,"yearly":0,"allTime":0},"commits":[]},{"date":"2026-01-06","stars":0,"forks":0,"downloads":{"monthly":0,"yearly":0,"allTime":0},"commits":[]},{"date":"2026-01-07","stars":0,"forks":0,"downloads":{"monthly":0,"yearly":0,"allTime":0},"commits":[]},{"date":"2026-01-08","stars":0,"forks":0,"downloads":{"monthly":0,"yearly":0,"allTime":0},"commits":[]},{"date":"2026-01-09","stars":0,"forks":0,"downloads":{"monthly":0,"yearly":0,"allTime":0},"commits":[]},{"date":"2026-01-10","stars":0,"forks":0,"downloads":{"monthly":0,"yearly":0,"allTime":0},"commits":[]},{"date":"2026-01-11","stars":0,"forks":0,"downloads":{"monthly":0,"yearly":0,"allTime":0},"commits":[{"year":2025,"count":7}]},{"date":"2026-01-19","stars":0,"forks":0,"downloads":{"monthly":0,"yearly":0,"allTime":0},"commits":[{"year":2025,"count":7}]}],"repos":[{"repoPath":"yowainwright/fasthar","current":{"stars":0,"forks":0,"commits":[{"year":2025,"count":7}],"activity":{"total":7,"years":[{"year":2025,"count":7}],"months":[{"month":"2025-09","commits":1},{"month":"2025-10","commits":1},{"month":"2025-11","commits":5}]}},"history":[{"date":"2026-01-09","stars":0,"forks":0,"commitsTotal":7},{"date":"2026-01-10","stars":0,"forks":0,"commits":[]},{"date":"2026-01-11","stars":0,"forks":0,"commits":[{"year":2025,"count":7}]},{"date":"2026-01-19","stars":0,"forks":0,"commits":[{"year":2025,"count":7}]}]}],"grade":{"score":0,"stars":0,"monthlyDownloads":0,"monthlyActivity":1,"commits":1}}